hackchat.py
hackchat-0.3.0.dist-info/LICENSE
hackchat-0.3.0.dist-info/METADATA
hackchat-0.3.0.dist-info/WHEEL
hackchat-0.3.0.dist-info/top_level.txt
hackchat-0.3.0.dist-info/RECORD
