Metadata-Version: 2.1
Name: hackchat
Version: 0.3.0
Summary: An event-driven hack.chat client library.
Home-page: https://github.com/gkbrk/hackchat
Author: Gokberk Yaltirakli
Author-email: webdosusb@gmail.com
Keywords: hack.chat,event,client,chat
License-File: LICENSE
Requires-Dist: websocket-client
